MANIFEST.in
README.md
setup.cfg
setup.py
kc_diagnostics/__init__.py
kc_diagnostics/cloud_processor.py
kc_diagnostics/diagnostics.py
kc_diagnostics/processor.py
kc_diagnostics.egg-info/PKG-INFO
kc_diagnostics.egg-info/SOURCES.txt
kc_diagnostics.egg-info/dependency_links.txt
kc_diagnostics.egg-info/requires.txt
kc_diagnostics.egg-info/top_level.txt
kc_diagnostics/resources/diagnostics-service-config-de.xml
kc_diagnostics/resources/diagnostics-service-config-es.xml
kc_diagnostics/resources/diagnostics-service-config-fr.xml
kc_diagnostics/resources/diagnostics-service-config-it.xml
kc_diagnostics/resources/diagnostics-service-config-pt.xml
kc_diagnostics/resources/diagnostics-service-config.xml