Metadata-Version: 2.1
Name: kc-diagnostics
Version: 1.0.5
Summary: Package to generate diagnostics messages.
Home-page: https://github.com/fawad1985/kc-diagnostics
Author: Fawad Mazhar
Author-email: fawad.mazhar@nordcloud.com
License: UNKNOWN
Download-URL: https://github.com/fawad1985/kc-diagnostics/archive/1.0.5.tar.gz
Keywords: AWS,IoT,Diagnostics,Lambda
Platform: UNKNOWN
Classifier: Programming Language :: Python :: 2.7
Classifier: License :: OSI Approved :: MIT License
Classifier: Operating System :: OS Independent
